MANIFEST.in
README.md
requirements.txt
setup.cfg
setup.py
slotty/__init__.py
slotty/datasimulator.py
slotty.datasimulator.egg-info/PKG-INFO
slotty.datasimulator.egg-info/SOURCES.txt
slotty.datasimulator.egg-info/dependency_links.txt
slotty.datasimulator.egg-info/entry_points.txt
slotty.datasimulator.egg-info/not-zip-safe
slotty.datasimulator.egg-info/requires.txt
slotty.datasimulator.egg-info/top_level.txt