Metadata-Version: 1.1
Name: slotty.datasimulator
Version: 0.1dev
Summary: Carrera Racing Unit data simulator for slotty
Home-page: UNKNOWN
Author: Rainer Schuster
Author-email: rainerschuster79@gmail.com
License: UNKNOWN
Keywords: RMS flask Slotcar slotty
Platform: UNKNOWN
Classifier: Development Status :: 3 - Alpha
Classifier: Environment :: Plugins
Classifier: Environment :: Web Environment
Classifier: Framework :: Flask
Classifier: Intended Audience :: Developers
Classifier: Natural Language :: English
Classifier: Operating System :: MacOS :: MacOS X
Classifier: Operating System :: POSIX :: Linux
Classifier: Programming Language :: Python :: 2.7
